MANIFEST.in
README.md
setup.py
twinge/__init__.py
twinge/cli.py
twinge/client.py
twinge.egg-info/PKG-INFO
twinge.egg-info/SOURCES.txt
twinge.egg-info/dependency_links.txt
twinge.egg-info/entry_points.txt
twinge.egg-info/not-zip-safe
twinge.egg-info/requires.txt
twinge.egg-info/top_level.txt