Metadata-Version: 1.0
Name: twinge
Version: 0.2.3
Summary: CLI for Twitch.tv
Home-page: https://github.com/scwood/twinge
Author: Spencer Wood
Author-email: spencercwood@gmail.com
License: UNKNOWN
Platform: UNKNOWN
